membershipUNOB/__init__.py
membershipUNOB/main.py
membershipUNOB/gql/__init__.py
membershipUNOB/gql/group_add.gql
membershipUNOB/gql/membership_add.gql
membershipUNOB/gql/user_add.gql
membershipUNOB/utils/__init__.py
membershipUNOB/utils/_config.py
membershipUNOB/utils/a_login.py
membershipUNOB/utils/b_get_group.py
membershipUNOB/utils/b_list_groups.html
membershipUNOB/utils/c_get_student.py
membershipUNOB/utils/d_create_externalids.py
membershipUNOB/utils/extract_data.py
membershipUNOB/utils/f_data_import.py
membershipUNOB-2.0.1.dist-info/METADATA
membershipUNOB-2.0.1.dist-info/WHEEL
membershipUNOB-2.0.1.dist-info/top_level.txt
membershipUNOB-2.0.1.dist-info/RECORD
