Metadata-Version: 2.1
Name: membershipUNOB
Version: 2.0.1
Summary: Membership management for UNOB
Home-page: https://github.com/getbricked/membershipunob
Author: Minh Quang Bui - Quang Tai Do
Author-email: minhquang.bui@unob.cz
Classifier: Programming Language :: Python :: 3
Classifier: Operating System :: OS Independent
Requires-Python: >=3.10
Requires-Dist: beautifulsoup4
Requires-Dist: requests
Requires-Dist: selenium
Requires-Dist: webdriver-manager
Requires-Dist: aiohttp
Requires-Dist: asyncpg
Requires-Dist: aiodataloader
Requires-Dist: async-lru
